AUTHORS.rst
CONTRIBUTING.rst
HISTORY.rst
LICENSE
MANIFEST.in
README.rst
setup.cfg
setup.py
django_management_audit.egg-info/PKG-INFO
django_management_audit.egg-info/SOURCES.txt
django_management_audit.egg-info/dependency_links.txt
django_management_audit.egg-info/not-zip-safe
django_management_audit.egg-info/top_level.txt
management_audit/__init__.py
management_audit/models.py