Metadata-Version: 1.1
Name: django-management-audit
Version: 0.1.0
Summary: Easily audit Django management commands
Home-page: https://github.com/hiisi13/django-management-audit
Author: Dmitry Kozhedubov
Author-email: dmitry-kozhedubov@yandex.ru
License: BSD
Keywords: django-management-audit
Platform: UNKNOWN
Classifier: Development Status :: 2 - Pre-Alpha
Classifier: Framework :: Django
Classifier: Intended Audience :: Developers
Classifier: License :: OSI Approved :: BSD License
Classifier: Natural Language :: English
Classifier: Programming Language :: Python :: 2
Classifier: Programming Language :: Python :: 2.6
Classifier: Programming Language :: Python :: 2.7
Classifier: Programming Language :: Python :: 3
Classifier: Programming Language :: Python :: 3.3
